README.md
setup.py
octo_train/__init__.py
octo_train/codeforces.py
octo_train/colored.py
octo_train/db.py
octo_train/euler.py
octo_train/main.py
octo_train/source_interface.py
octo_train.egg-info/PKG-INFO
octo_train.egg-info/SOURCES.txt
octo_train.egg-info/dependency_links.txt
octo_train.egg-info/entry_points.txt
octo_train.egg-info/requires.txt
octo_train.egg-info/top_level.txt