Metadata-Version: 2.1
Name: octo-train
Version: 0.1.2
Summary: Console application to make you a great programmer.
Home-page: https://github.com/dankondr/octo-train
Author: dankondr
Author-email: dankondr@icloud.com
License: UNKNOWN
Platform: UNKNOWN
Classifier: Development Status :: 3 - Alpha
Classifier: License :: OSI Approved :: MIT License
Requires-Python: >=3.7
